trivia/__init__.py
trivia/utils/__init__.py
opentdb_py-2.1.2.dist-info/LICENSE
opentdb_py-2.1.2.dist-info/METADATA
opentdb_py-2.1.2.dist-info/WHEEL
opentdb_py-2.1.2.dist-info/top_level.txt
opentdb_py-2.1.2.dist-info/RECORD
