Metadata-Version: 2.1
Name: opentdb-py
Version: 2.1.2
Summary: Python wrapper for the open-trivia-database API
Home-page: https://github.com/Marseel-E/opentdb-py
Author: Marseel Eeso
Author-email: marseeleeso@gmail.com
License: UNKNOWN
Project-URL: Bug Tracker, https://github.com/Marseel-E/opentdb-py/issues
Platform: UNKNOWN
Classifier: Programming Language :: Python :: 3
Classifier: License :: OSI Approved :: MIT License
Classifier: Operating System :: OS Independent
Requires-Python: >=3.8
License-File: LICENSE
